caasm_aql/__init__.py
caasm_aql/aql.py
caasm_aql/aql_context.py
caasm_aql/aql_error.py
caasm_aql/aql_resolver.py
caasm_aql/asgl.py
caasm_aql/asgl_resolver.py
caasm_aql/asql_batch.py
caasm_aql/asql_field.py
caasm_aql/asql_fulltext.py
caasm_aql/asql_plus.py
caasm_aql/base.py
caasm_aql/entity_id_field_name_getter.py
caasm_aql/field_data_type_getter.py
caasm_aql/querier.py
caasm_aql/schemas.py
caasm_aql/filter/__init__.py
caasm_aql/filter/builder.py
caasm_aql/filter/filter.py
caasm_aql/filter/method.py
caasm_aql/filter/method_manager.py
caasm_aql/filter/op.py
caasm_aql/filter/op_manager.py
caasm_aql/filter/filters/__init__.py
caasm_aql/filter/filters/field.py
caasm_aql/filter/filters/group.py
caasm_aql/filter/filters/method.py
caasm_aql/filter/filters/op.py
caasm_aql/filter/methods/__init__.py
caasm_aql/filter/methods/ends.py
caasm_aql/filter/methods/exists.py
caasm_aql/filter/methods/in_.py
caasm_aql/filter/methods/match.py
caasm_aql/filter/methods/regex.py
caasm_aql/filter/methods/size.py
caasm_aql/filter/methods/starts.py
caasm_aql/filter/ops/__init__.py
caasm_aql/filter/ops/eq.py
caasm_aql/filter/ops/gt.py
caasm_aql/filter/ops/gte.py
caasm_aql/filter/ops/lt.py
caasm_aql/filter/ops/lte.py
caasm_aql/filter/ops/ne.py
caasm_aql/queriers/__init__.py
caasm_aql/queriers/_base.py
caasm_aql/queriers/es.py
caasm_aql/queriers/orient.py
caasm_aql/query_builders/__init__.py
caasm_aql/query_builders/converter.py
caasm_aql/query_builders/function.py
caasm_aql/query_builders/fuzzy_provider.py
caasm_aql/query_builders/method.py
caasm_aql/query_builders/operator.py
caasm_aql/query_builders/runtime.py
caasm_aql/query_builders/backend/__init__.py
caasm_aql/query_builders/backend/_base.py
caasm_aql/query_builders/backend/es.py
caasm_aql/query_builders/backend/orient.py
caasm_aql/query_builders/es/__init__.py
caasm_aql/query_builders/es/util.py
caasm_aql/query_builders/es/converters/__init__.py
caasm_aql/query_builders/es/converters/bool.py
caasm_aql/query_builders/es/converters/date.py
caasm_essence-0.1.21.2.dist-info/METADATA
caasm_essence-0.1.21.2.dist-info/WHEEL
caasm_essence-0.1.21.2.dist-info/top_level.txt
caasm_essence-0.1.21.2.dist-info/RECORD
